{
  "meta": {
    "generated": "Jul 12, 2026",
    "window": "Last 30 days",
    "accounts": 4,
    "totalSpend": "$104,911",
    "totalImpressions": "4.1M"
  },
  "regions": [
    {
      "key": "na",
      "label": "North America",
      "spend": 53970,
      "impressions": 1514791,
      "clicks": 7406,
      "ctr": 0.0049,
      "cpm": 35.63,
      "cpc": 7.29
    },
    {
      "key": "emea",
      "label": "EMEA",
      "spend": 40450,
      "impressions": 1535546,
      "clicks": 5786,
      "ctr": 0.0038,
      "cpm": 26.34,
      "cpc": 6.99
    },
    {
      "key": "apac",
      "label": "APAC",
      "spend": 2061,
      "impressions": 389669,
      "clicks": 329,
      "ctr": 0.0008,
      "cpm": 5.29,
      "cpc": 6.26
    },
    {
      "key": "latam",
      "label": "LATAM",
      "spend": 8430,
      "impressions": 624094,
      "clicks": 2602,
      "ctr": 0.0042,
      "cpm": 13.51,
      "cpc": 3.24
    }
  ],
  "trend": [
    {
      "wk": "Wk20",
      "na": 11974.54,
      "emea": 7086.92,
      "apac": 954.62,
      "latam": 1703.37
    },
    {
      "wk": "Wk21",
      "na": 11831.68,
      "emea": 6452.29,
      "apac": 5650.69,
      "latam": 1676.32
    },
    {
      "wk": "Wk22",
      "na": 12685.49,
      "emea": 6806.68,
      "apac": 5078.91,
      "latam": 1675.68
    },
    {
      "wk": "Wk23",
      "na": 13250.3,
      "emea": 7322.5,
      "apac": 1230.46,
      "latam": 1959.32
    },
    {
      "wk": "Wk24",
      "na": 13781.67,
      "emea": 9027.46,
      "apac": 583.96,
      "latam": 1652.1
    },
    {
      "wk": "Wk25",
      "na": 12830.08,
      "emea": 8535.79,
      "apac": 465.41,
      "latam": 1649.65
    },
    {
      "wk": "Wk26",
      "na": 12861.18,
      "emea": 8413.55,
      "apac": 482.49,
      "latam": 2082.51
    },
    {
      "wk": "Wk27",
      "na": 13417.9,
      "emea": 10446.47,
      "apac": 489.61,
      "latam": 2153.36
    }
  ],
  "naCampaigns": [
    {
      "n": "Always On - Retargeting",
      "spend": 4886.46,
      "impr": 430348,
      "clicks": 677,
      "ctr": 0.0016,
      "cpm": 11.35,
      "cpc": 7.22,
      "eng": 1051
    },
    {
      "n": "Integrated Marketing",
      "spend": 11163.1,
      "impr": 221876,
      "clicks": 789,
      "ctr": 0.0036,
      "cpm": 50.31,
      "cpc": 14.15,
      "eng": 1442
    },
    {
      "n": "Vocational 2026 | $5K",
      "spend": 5021.21,
      "impr": 206017,
      "clicks": 746,
      "ctr": 0.0036,
      "cpm": 24.37,
      "cpc": 6.73,
      "eng": 1237
    },
    {
      "n": "Public Sector 2026 | $10K",
      "spend": 9534.13,
      "impr": 175749,
      "clicks": 1032,
      "ctr": 0.0059,
      "cpm": 54.25,
      "cpc": 9.24,
      "eng": 1615
    },
    {
      "n": "ABX BA - 2026",
      "spend": 1618.06,
      "impr": 159612,
      "clicks": 69,
      "ctr": 0.0004,
      "cpm": 10.14,
      "cpc": 23.45,
      "eng": 77
    },
    {
      "n": "Transportation & Logistics 2026 | $8K ($7k in July)",
      "spend": 6954.62,
      "impr": 152230,
      "clicks": 778,
      "ctr": 0.0051,
      "cpm": 45.69,
      "cpc": 8.94,
      "eng": 1230
    },
    {
      "n": "Field Service 2026 | $7.5K",
      "spend": 6895.54,
      "impr": 68312,
      "clicks": 2112,
      "ctr": 0.0309,
      "cpm": 100.94,
      "cpc": 3.26,
      "eng": 3349
    },
    {
      "n": "Car Rental & Leasing 2026 | $5K",
      "spend": 5225.7,
      "impr": 65831,
      "clicks": 850,
      "ctr": 0.0129,
      "cpm": 79.38,
      "cpc": 6.15,
      "eng": 1320
    },
    {
      "n": "ABX WV - 2026",
      "spend": 2671.02,
      "impr": 34816,
      "clicks": 353,
      "ctr": 0.0101,
      "cpm": 76.72,
      "cpc": 7.57,
      "eng": 554
    }
  ],
  "emeaCampaigns": [
    {
      "n": "Always on retargeting",
      "spend": 6795.01,
      "impr": 446136,
      "clicks": 926,
      "ctr": 0.0021,
      "cpm": 15.23,
      "cpc": 7.34
    },
    {
      "n": "Services",
      "spend": 7840.03,
      "impr": 313015,
      "clicks": 1050,
      "ctr": 0.0034,
      "cpm": 25.05,
      "cpc": 7.47
    },
    {
      "n": "Always on - cold",
      "spend": 4671.63,
      "impr": 154378,
      "clicks": 613,
      "ctr": 0.004,
      "cpm": 30.26,
      "cpc": 7.62
    },
    {
      "n": "LRM",
      "spend": 3885.17,
      "impr": 126005,
      "clicks": 660,
      "ctr": 0.0052,
      "cpm": 30.83,
      "cpc": 5.89
    },
    {
      "n": "Transport and Logistics",
      "spend": 3306.29,
      "impr": 110134,
      "clicks": 536,
      "ctr": 0.0049,
      "cpm": 30.02,
      "cpc": 6.17
    },
    {
      "n": "People Transportation",
      "spend": 3824.78,
      "impr": 106725,
      "clicks": 461,
      "ctr": 0.0043,
      "cpm": 35.84,
      "cpc": 8.3
    },
    {
      "n": "Sustainability",
      "spend": 5037.67,
      "impr": 97552,
      "clicks": 253,
      "ctr": 0.0026,
      "cpm": 51.64,
      "cpc": 19.91
    },
    {
      "n": "EMEA Safety",
      "spend": 2830.36,
      "impr": 93183,
      "clicks": 633,
      "ctr": 0.0068,
      "cpm": 30.37,
      "cpc": 4.47
    },
    {
      "n": "World Cup 2026",
      "spend": 1588.85,
      "impr": 55637,
      "clicks": 188,
      "ctr": 0.0034,
      "cpm": 28.56,
      "cpc": 8.45
    },
    {
      "n": "Boost_Post_Engagement_Mar 10, 2026",
      "spend": 229.19,
      "impr": 17426,
      "clicks": 361,
      "ctr": 0.0207,
      "cpm": 13.15,
      "cpc": 0.63
    },
    {
      "n": "EMEA Fuel",
      "spend": 412.96,
      "impr": 14321,
      "clicks": 103,
      "ctr": 0.0072,
      "cpm": 28.84,
      "cpc": 4.01
    },
    {
      "n": "KINTO RFP Enterprise: EMEA",
      "spend": 28,
      "impr": 1034,
      "clicks": 2,
      "ctr": 0.0019,
      "cpm": 27.08,
      "cpc": 14
    }
  ],
  "seniority": [
    {
      "s": "Senior",
      "impr": 684438,
      "clicks": 3017
    },
    {
      "s": "Manager",
      "impr": 229233,
      "clicks": 1278
    },
    {
      "s": "Director",
      "impr": 223307,
      "clicks": 870
    },
    {
      "s": "VP",
      "impr": 136515,
      "clicks": 736
    },
    {
      "s": "CXO",
      "impr": 94086,
      "clicks": 443
    },
    {
      "s": "Entry",
      "impr": 65411,
      "clicks": 673
    },
    {
      "s": "Owner",
      "impr": 37622,
      "clicks": 235
    }
  ],
  "functions": [
    {
      "f": "Operations",
      "impr": 607025,
      "clicks": 3242
    },
    {
      "f": "Business Development",
      "impr": 319288,
      "clicks": 1260
    },
    {
      "f": "Sales",
      "impr": 80169,
      "clicks": 690
    },
    {
      "f": "IT",
      "impr": 189728,
      "clicks": 505
    },
    {
      "f": "Engineering",
      "impr": 105026,
      "clicks": 489
    },
    {
      "f": "Customer Success",
      "impr": 61496,
      "clicks": 454
    },
    {
      "f": "Finance",
      "impr": 89566,
      "clicks": 426
    },
    {
      "f": "Education",
      "impr": 66791,
      "clicks": 406
    },
    {
      "f": "PM/Project Mgmt",
      "impr": 45024,
      "clicks": 315
    },
    {
      "f": "Healthcare",
      "impr": 26364,
      "clicks": 291
    }
  ]
}
